nb_itsm/__init__.py
nb_itsm/api/__init__.py
nb_itsm/api/serializers.py
nb_itsm/api/urls.py
nb_itsm/api/views.py
nb_itsm/choices.py
nb_itsm/filtersets.py
nb_itsm/forms.py
nb_itsm/migrations/0001_initial.py
nb_itsm/migrations/__init__.py
nb_itsm/models.py
nb_itsm/navigation.py
nb_itsm/signals.py
nb_itsm/static/nb_itsm/export_svg.js
nb_itsm/static/nb_itsm/mermaid.min.js
nb_itsm/static/nb_itsm/mermaid.min.js.map
nb_itsm/tables.py
nb_itsm/templates/nb_itsm/application.html
nb_itsm/templates/nb_itsm/application_objs.html
nb_itsm/templates/nb_itsm/pentest.html
nb_itsm/templates/nb_itsm/relation.html
nb_itsm/templates/nb_itsm/service-configuration-item-view.html
nb_itsm/templates/nb_itsm/service.html
nb_itsm/templates/nb_itsm/service_Relation_view.html
nb_itsm/templates/nb_itsm/service_diagram_view.html
nb_itsm/tests/__init__.py
nb_itsm/tests/application/__init__.py
nb_itsm/tests/application/test_api.py
nb_itsm/tests/application/test_filters.py
nb_itsm/tests/application/test_views.py
nb_itsm/tests/custom.py
nb_itsm/tests/service/__init__.py
nb_itsm/tests/service/test_api.py
nb_itsm/tests/service/test_filters.py
nb_itsm/tests/service/test_views.py
nb_itsm/urls.py
nb_itsm/version.py
nb_itsm/views.py
nb_itsm-0.13.1.dist-info/METADATA
nb_itsm-0.13.1.dist-info/WHEEL
nb_itsm-0.13.1.dist-info/licenses/LICENSE
nb_itsm-0.13.1.dist-info/licenses/NOTICE
nb_itsm-0.13.1.dist-info/RECORD
