Metadata-Version: 2.4
Name: nb_itsm
Version: 0.13.1
Summary: ITIL Services, Applications & more
License: Apache-2.0
License-File: LICENSE
License-File: NOTICE
Author: CISPA IT Department
Author-email: admin@cispa.de
Maintainer: Sebastian Weisgerber
Maintainer-email: weisgerber@cispa.de
Requires-Python: >=3.10,<4.0
Classifier: Development Status :: 3 - Alpha
Classifier: Environment :: Plugins
Classifier: Environment :: Web Environment
Classifier: Framework :: Django
Classifier: License :: OSI Approved :: Apache Software License
Classifier: Programming Language :: Python :: 3
Classifier: Programming Language :: Python :: 3.10
Classifier: Programming Language :: Python :: 3.11
Classifier: Programming Language :: Python :: 3.12
Classifier: Programming Language :: Python :: 3.13
Classifier: Programming Language :: Python :: 3.14
Requires-Dist: Django (==5.2.7)
Project-URL: Repository, https://projects.cispa.saarland/it/services/itsm/netbox-plugin-itsm
